gobigger/__init__.py
gobigger/agents/__init__.py
gobigger/agents/base_agent.py
gobigger/agents/bot_agent.py
gobigger/balls/__init__.py
gobigger/balls/base_ball.py
gobigger/balls/clone_ball.py
gobigger/balls/food_ball.py
gobigger/balls/spore_ball.py
gobigger/balls/thorns_ball.py
gobigger/bin/__init__.py
gobigger/bin/demo_bot.py
gobigger/bin/play.py
gobigger/bin/play_hyper.py
gobigger/bin/profile.py
gobigger/bin/replayer.py
gobigger/configs/__init__.py
gobigger/configs/server_default_config.py
gobigger/configs/server_sp_default_config.py
gobigger/configs/sp_t4p3.py
gobigger/configs/st_t1p1.py
gobigger/configs/st_t1p2.py
gobigger/configs/st_t2p1.py
gobigger/configs/st_t2p2.py
gobigger/configs/st_t3p2.py
gobigger/configs/st_t4p3.py
gobigger/configs/st_t5p3.py
gobigger/configs/st_t5p4.py
gobigger/configs/st_t6p4.py
gobigger/envs/__init__.py
gobigger/envs/gobigger_env.py
gobigger/envs/gobigger_sp_env.py
gobigger/managers/__init__.py
gobigger/managers/base_manager.py
gobigger/managers/food_manager.py
gobigger/managers/player_manager.py
gobigger/managers/player_sp_manager.py
gobigger/managers/spore_manager.py
gobigger/managers/thorns_manager.py
gobigger/playbacks/__init__.py
gobigger/playbacks/action_pb.py
gobigger/playbacks/base_pb.py
gobigger/playbacks/frame_pb.py
gobigger/playbacks/null_pb.py
gobigger/playbacks/video_pb.py
gobigger/players/__init__.py
gobigger/players/base_player.py
gobigger/players/human_player.py
gobigger/players/human_sp_player.py
gobigger/render/__init__.py
gobigger/render/base_render.py
gobigger/render/env_render.py
gobigger/render/pb_render.py
gobigger/render/realtime_render.py
gobigger/server/__init__.py
gobigger/server/server.py
gobigger/server/server_sp.py
gobigger/utils/__init__.py
gobigger/utils/collision_detection.py
gobigger/utils/colors.py
gobigger/utils/config_utils.py
gobigger/utils/frame_utils.py
gobigger/utils/generator_utils.py
gobigger/utils/obs_utils.py
gobigger/utils/structures.py
gobigger/utils/tool.py
gobigger-0.2.1.dist-info/LICENSE
gobigger-0.2.1.dist-info/METADATA
gobigger-0.2.1.dist-info/WHEEL
gobigger-0.2.1.dist-info/top_level.txt
gobigger-0.2.1.dist-info/RECORD
